ai/__init__.py
ai/build_v2.py
cli/__init__.py
cli/cli.py
clients/__init__.py
clients/config.py
files/__init__.py
files/check_mimetype.py
files/file_management.py
files/file_upload.py
utils/__init__.py
utils/constants.py
utils/errors.py
utils/logs.py
ai_code_refinement-0.0.8.dist-info/METADATA
ai_code_refinement-0.0.8.dist-info/WHEEL
ai_code_refinement-0.0.8.dist-info/entry_points.txt
ai_code_refinement-0.0.8.dist-info/top_level.txt
ai_code_refinement-0.0.8.dist-info/RECORD
